readmegen_cli-0.1.4.dist-info/licenses/LICENSE
readmegen_core/__init__.py
readmegen_core/cli.py
readmegen_core/generate.py
readmegen_core/local_inspector.py
readmegen_cli-0.1.4.dist-info/METADATA
readmegen_cli-0.1.4.dist-info/WHEEL
readmegen_cli-0.1.4.dist-info/entry_points.txt
readmegen_cli-0.1.4.dist-info/top_level.txt
readmegen_cli-0.1.4.dist-info/RECORD
