Metadata-Version: 2.4
Name: readmegen-cli
Version: 0.1.4
Summary: Generate professional README.md files using AI.
Home-page: https://github.com/inevitablegs/git-readme
Author: Ganesh Sonawane
Author-email: sonawaneganu3101@gmail.com
License: MIT
Classifier: Programming Language :: Python :: 3
Classifier: License :: OSI Approved :: MIT License
Classifier: Operating System :: OS Independent
Requires-Python: >=3.7
License-File: LICENSE
Requires-Dist: google-generativeai==0.8.4
Requires-Dist: python-dotenv==1.0.1
Dynamic: author
Dynamic: author-email
Dynamic: classifier
Dynamic: description
Dynamic: description-content-type
Dynamic: home-page
Dynamic: license
Dynamic: license-file
Dynamic: requires-dist
Dynamic: requires-python
Dynamic: summary
